TODO LIST:
  1. RESOLVER CENA DO MENOS
  4. FAZER ALTO REFACTORING NESTE TRETA
  9. Check cena do string&array -> se é [S
  15. CODIGO PARA variavel.length -> arraylength?
  17. Nao me cheira que isto esteja bem -> ios/pp(LC;;)I
  18. Verificar instruçoes (nomeadamente aload 1/0 true/false)
  19. Verificar expressoes aritmeticas
  20. ver while true/false -> verificar em casos com muitos loops e ifs encadeados
  22. 

************************************************************************
    public void Test(int[] array) {
        System.out.println(new Symbol().toString());

         public void Test(int[]);
    Code:
       0: getstatic     #19                 // Field java/lang/System.out:Ljava/io/PrintStream;
       3: new           #20                 // class Symbol
       6: dup
       7: invokespecial #21                 // Method "<init>":()V
      10: invokevirtual #22                 // Method toString:()Ljava/lang/String;
      13: invokevirtual #23                 // Method java/io/PrintStream.println:(Ljava/lang/String;)V
      16: return
    }

************************************************************************
     public void Test(int[] array) {
        System.out.println(new Symbol().getCounter(1));
    }

    public void Test(int[]);
    Code:
       0: getstatic     #19                 // Field java/lang/System.out:Ljava/io/PrintStream;       3: new           #20                 // class Symbol
       6: dup
       7: invokespecial #21                 // Method "<init>":()V
      10: iconst_1
      11: invokevirtual #22                 // Method getCounter:(I)I
      14: invokevirtual #23                 // Method java/io/PrintStream.println:(I)V
      17: return}

************************************************************************
    public void Test(int[] array) {
        int x = new Symbol().getCounter(1);
    }

     public void Test(int[]);
    Code:
       0: new           #19                 // class Symbol
       3: dup
       4: invokespecial #20                 // Method "<init>":()V
       7: iconst_1
       8: invokevirtual #21                 // Method getCounter:(I)I
      11: istore_2
      12: return

************************************************************************
    public void Test(int[] array) {
        int x = new Symbol().getCounter(1);
        boolean a = x < 1;
    }

    public void Test(int[]);
    Code:
       0: new           #19                 // class Symbol
       3: dup
       4: invokespecial #20                 // Method "<init>":()V
       7: iconst_1
       8: invokevirtual #21                 // Method getCounter:(I)I
      11: istore_2
      12: iload_2
      13: iconst_1
      14: if_icmpge     21
      17: iconst_1
      18: goto          22
      21: iconst_0
      22: istore_3
      23: return

************************************************************************
  public void Test(int[] array) {
        //int x = new Symbol().getCounter(1);
        int x = 10;
        int c = 1;
        if (x < 123) 
            c = 1;
        else 
        c = 0 ;
    }

 public void Test(int[]);
    Code:
       0: bipush        10
       2: istore_2
       3: iconst_1
       4: istore_3
       5: iload_2
       6: bipush        123
       8: if_icmpge     16
      11: iconst_1
      12: istore_3
      13: goto          18
      16: iconst_0
      17: istore_3
      18: return

************************************************************************
   public void Test(int[] array) {
        //int x = new Symbol().getCounter(1);
        boolean x = true;
        int c = 1;
        if (x) 
            c = 1;
        else 
        c = 0 ;
    }


    public void Test(int[]);
    Code:
       0: iconst_1
       1: istore_2
       2: iconst_1
       3: istore_3
       4: iload_2
       5: ifeq          13
       8: iconst_1
       9: istore_3
      10: goto          15
      13: iconst_0
      14: istore_3
      15: return

************************************************************************
    public void Test(int[] array) {
        //int x = new Symbol().getCounter(1);
        boolean x = true;
        int c = 1;
        if (true) 
            c = 1;
        else 
        c = 0 ;  //dead code
    }

 public void Test(int[]);
    Code:
       0: iconst_1
       1: istore_2
       2: iconst_1
       3: istore_3
       4: iconst_1
       5: istore_3
       6: return


************************************************************************
 public void Test(int[] array) {
        //int x = new Symbol().getCounter(1);
        boolean x = true;
        int c = 1;
        if (check_test()) 
            c = 1;
        else 
        c = 0 ;
    }

 public void Test(int[]);
    Code:
       0: iconst_1
       1: istore_2
       2: iconst_1
       3: istore_3
       4: aload_0
       5: invokevirtual #16                 // Method check_test:()Z
       8: ifeq          16
      11: iconst_1
      12: istore_3
      13: goto          18
      16: iconst_0
      17: istore_3
      18: return

************************************************************************
   public void Test(int[] array) {
        //int x = new Symbol().getCounter(1);
        boolean x = true;
        int c = 1;
        if (check_test(true) && x) 
            c = 1;
        else 
            c = 0 ;
    }

    public void Test(int[]);
    Code:
       0: iconst_1
       1: istore_2
       2: iconst_1
       3: istore_3
       4: aload_0
       5: iconst_1
       6: invokevirtual #16                 // Method check_test:(Z)Z
       9: ifeq          21
      12: iload_2
      13: ifeq          21
      16: iconst_1
      17: istore_3
      18: goto          23
      21: iconst_0
      22: istore_3
      23: return


************************************************************************
 public void Test(int[] array) {
        //int x = new Symbol().getCounter(1);
        boolean x = true;
        int c = 1;
        if (check_test(true) && x) 
            c = 1;
        else 
            c = 0 ;
}

public void Test(int[]);
    Code:
       0: iconst_1
       1: istore_2
       2: iconst_1
       3: istore_3
       4: aload_0
       5: iconst_1
       6: invokevirtual #16                 // Method check_test:(Z)Z
       9: ifeq          21
      12: iload_2
      13: ifeq          21
      16: iconst_1
      17: istore_3
      18: goto          23
      21: iconst_0
      22: istore_3
      23: return

************************************************************************
  public void Test(int[] array) {
        //int x = new Symbol().getCounter(1);
        boolean a= true;
        int c = 1;
        while(a) {
            c = c+1;
        } 
    }

 public void Test(int[]);
    Code:
       0: iconst_1
       1: istore_2
       2: iconst_1
       3: istore_3
       4: iload_2
       5: ifeq          15
       8: iload_3
       9: iconst_1
      10: iadd
      11: istore_3
      12: goto          4
      15: return

************************************************************************
 public void Test(int[] array) {
        //int x = new Symbol().getCounter(1);
        boolean a= true;
        int c = 1;
        while(a && c < 1) {
            c = c+1;
        } 
    }

 public void Test(int[]);
    Code:
       0: iconst_1
       1: istore_2
       2: iconst_1
       3: istore_3
       4: iload_2
       5: ifeq          20
       8: iload_3
       9: iconst_1
      10: if_icmpge     20
      13: iload_3
      14: iconst_1
      15: iadd
      16: istore_3
      17: goto          4
      20: return

************************************************************************
